README.md
setup.cfg
setup.py
foxtail_trainer_api/__init__.py
foxtail_trainer_api/api_client.py
foxtail_trainer_api/configuration.py
foxtail_trainer_api/exceptions.py
foxtail_trainer_api/model_utils.py
foxtail_trainer_api/rest.py
foxtail_trainer_api.egg-info/PKG-INFO
foxtail_trainer_api.egg-info/SOURCES.txt
foxtail_trainer_api.egg-info/dependency_links.txt
foxtail_trainer_api.egg-info/requires.txt
foxtail_trainer_api.egg-info/top_level.txt
foxtail_trainer_api/api/__init__.py
foxtail_trainer_api/api/custom_metric_api.py
foxtail_trainer_api/api/data_set_chunk_api.py
foxtail_trainer_api/api/job_api.py
foxtail_trainer_api/api/ml_model_api.py
foxtail_trainer_api/api/ml_model_with_training_result_api.py
foxtail_trainer_api/api/prediction_task_api.py
foxtail_trainer_api/api/report_api.py
foxtail_trainer_api/api/training_config_api.py
foxtail_trainer_api/api/training_result_api.py
foxtail_trainer_api/api/worker_api.py
foxtail_trainer_api/apis/__init__.py
foxtail_trainer_api/model/__init__.py
foxtail_trainer_api/model/add_or_update_model_hyperparameter.py
foxtail_trainer_api/model/add_or_update_model_hyperparameter_in_job.py
foxtail_trainer_api/model/aggregated_metric_report_dto.py
foxtail_trainer_api/model/create_custom_metric_dto.py
foxtail_trainer_api/model/create_data_sets_sizes_dto.py
foxtail_trainer_api/model/create_job_command.py
foxtail_trainer_api/model/create_metric_dto.py
foxtail_trainer_api/model/create_ml_model_dto.py
foxtail_trainer_api/model/create_ml_models_command.py
foxtail_trainer_api/model/create_model_hyperparameter_dto.py
foxtail_trainer_api/model/create_prediction_task_command.py
foxtail_trainer_api/model/create_training_config_dto.py
foxtail_trainer_api/model/create_training_history_dto.py
foxtail_trainer_api/model/create_training_result_command.py
foxtail_trainer_api/model/create_training_result_dto.py
foxtail_trainer_api/model/created_job_dto.py
foxtail_trainer_api/model/created_ml_models_dto.py
foxtail_trainer_api/model/created_prediction_task_dto.py
foxtail_trainer_api/model/custom_metric_dto.py
foxtail_trainer_api/model/custom_model_hyperparameter_dto.py
foxtail_trainer_api/model/custom_model_hyperparameter_with_model_dto.py
