Metadata-Version: 1.2
Name: foxtail-trainer-api
Version: 0.5.1
Summary: Foxtail Trainer
Home-page: https://pypi.org/project/foxtail-trainer-api/
Author: OpenAPI Generator community
Author-email: team@openapitools.org
License: UNKNOWN
Keywords: OpenAPI,OpenAPI-Generator,Foxtail Trainer
Platform: UNKNOWN
Requires-Python: >=3.6
